{
    "clasifications": 
    [
        {
            "classification_name": "coffee_type",
            "model_path": "resources/MLmodels/coffee_type_classification/coffee_type_classification_v1.pt",
            "class_labels": [
                "cappuccino",
                "espresso",
                "black_coffee"
            ]
        },
        {
            "classification_name": "crema",
            "model_path": "resources/MLmodels/crema_classification/crema_classification_v1.pt",
            "class_labels": [
                "false",
                "true"
            ]
        },
        {
            "classification_name": "served_way",
            "model_path": "resources/MLmodels/served_way_classification/served_way_classification_v1.pt",
            "class_labels": [
                "false",
                "true"
            ]
        },
        {
            "classification_name": "type_of_cup",
            "model_path": "resources/MLmodels/type_of_cup_classification/type_of_cup_classification_v1.pt",
            "class_labels": [
                "false",
                "true"
            ]
        }
    ],
    "coffee_detection": 
    {
        "model_path": "resources/MLmodels/object_detection/object_detection_v1.pt"
    }
}
